graylogcg/__init__.py
graylogcg/graylogcg.py
graylogcg-2.0.1.dist-info/LICENSE
graylogcg-2.0.1.dist-info/METADATA
graylogcg-2.0.1.dist-info/WHEEL
graylogcg-2.0.1.dist-info/top_level.txt
graylogcg-2.0.1.dist-info/RECORD
