Metadata-Version: 2.1
Name: graylogcg
Version: 2.0.1
Summary: Biblioteca para inserção de logs padronizados.
Home-page: https://github.com/ramirooliveiracg/graylogcg
Author: Gabriel Dalacorte e Rogerio Filho
Author-email: gnunes.servico@gmail.com, crofilho2@gmail.com
License: MIT
Classifier: License :: OSI Approved :: MIT License
Classifier: Programming Language :: Python :: 3
Classifier: Programming Language :: Python :: 3.7
License-File: LICENSE
Requires-Dist: graypy
